gilot/__init__.py
gilot/app.py
gilot/core.py
gilot/filetracker.py
gilot/hotgraph.py
gilot/hotspot.py
gilot/plotter.py
gilot-0.2.7.dist-info/licenses/LICENSE
gilot-0.2.7.dist-info/METADATA
gilot-0.2.7.dist-info/WHEEL
gilot-0.2.7.dist-info/entry_points.txt
gilot-0.2.7.dist-info/top_level.txt
gilot-0.2.7.dist-info/RECORD
