Metadata-Version: 2.4
Name: gilot
Version: 0.2.7
Summary: a git log visual analyzer
Requires-Python: >=3.12
License-File: LICENSE
Requires-Dist: argparse>=1.4.0
Requires-Dist: datetime>=5.5
Requires-Dist: gitpython>=3.1.44
Requires-Dist: matplotlib<3.8.0,>=3.7.5
Requires-Dist: networkx>=3.1
Requires-Dist: numpy>=1.26.0
Requires-Dist: pandas>=2.0.3
Requires-Dist: pyfpgrowth>=1.0
Requires-Dist: python-louvain>=0.16
Requires-Dist: scipy>=1.10.1
Requires-Dist: seaborn<0.13.0,>=0.12.0
Requires-Dist: timeout-decorator>=0.5.0
Dynamic: license-file
